README.md
setup.py
mime_extension/__init__.py
mime_extension/main.py
mime_extension.egg-info/PKG-INFO
mime_extension.egg-info/SOURCES.txt
mime_extension.egg-info/dependency_links.txt
mime_extension.egg-info/entry_points.txt
mime_extension.egg-info/requires.txt
mime_extension.egg-info/top_level.txt