Metadata-Version: 2.1
Name: mime-extension
Version: 1.1.0
Summary: Return the file extension for a mimetype on Linux
Home-page: https://github.com/talwrii/mime-extension
Author: @readwithai
Author-email: talwrii@gmail.com
License: MIT
Keywords: mime,extension,cli
